hotpod_cli/__init__.py
hotpod_cli/cli.py
hotpod_cli/gcs.py
hotpod_cli/image.json
hotpod_cli/main.py
hotpod_cli/sku.json
hotpod_cli/commands/__init__.py
hotpod_cli/commands/cluster.py
hotpod_cli/commands/comfyui.py
hotpod_cli/commands/file.py
hotpod_cli/commands/instance.py
hotpod_cli/commands/llm.py
hotpod_cli/tasks/.gitkeep
hotpod_cli/utils/__init__.py
hotpod_cli/utils/click_utils.py
hotpod_cli/utils/ssh.py
hotpod_cli-1.2.0.dist-info/METADATA
hotpod_cli-1.2.0.dist-info/WHEEL
hotpod_cli-1.2.0.dist-info/entry_points.txt
hotpod_cli-1.2.0.dist-info/top_level.txt
hotpod_cli-1.2.0.dist-info/RECORD
