Metadata-Version: 2.4
Name: hotpod-cli
Version: 1.2.0
Summary: A command line tool for GCS
Home-page: https://github.com/yourusername/hotpod
Author: Your Name
Author-email: JDCloud AIDC Team <your.email@example.com>
Project-URL: Homepage, https://github.com/yourusername/hotpod-cli
Classifier: Programming Language :: Python :: 3
Classifier: License :: OSI Approved :: MIT License
Classifier: Operating System :: OS Independent
Requires-Python: >=3.6
Requires-Dist: click>=8.1.8
Requires-Dist: setuptools>=78.0.2
Requires-Dist: click-help-colors>=0.9.1
Requires-Dist: click-option-group>=0.5.3
Requires-Dist: click-spinner>=0.1.10
Requires-Dist: jdcloud-sdk>=1.6.88
Requires-Dist: python-dotenv>=1.0.0
Requires-Dist: litellm==1.64.1
Requires-Dist: paramiko==3.4.0
Dynamic: author
Dynamic: home-page
Dynamic: requires-python
